torchviz/__init__.py
torchviz/dot.py
torchviz2-0.0.2.dist-info/LICENSE
torchviz2-0.0.2.dist-info/METADATA
torchviz2-0.0.2.dist-info/WHEEL
torchviz2-0.0.2.dist-info/top_level.txt
torchviz2-0.0.2.dist-info/zip-safe
torchviz2-0.0.2.dist-info/RECORD
