Metadata-Version: 2.1
Name: torchviz2
Version: 0.0.2
Summary: A small package to create visualizations of PyTorch execution graphs
Author: Leo Ware
Author-email: leoware@gmail.com
License: MIT
License-File: LICENSE
Requires-Dist: torch
Requires-Dist: graphviz
Requires-Dist: looseversion
